{
  "cover_relations": [
    "a<c",
    "a<d",
    "b<c",
    "b<e",
    "b<f",
    "c<g",
    "d<e",
    "d<f",
    "e<g"
  ],
  "depth": 3,
  "labels": [
    "a",
    "b",
    "c",
    "d",
    "e",
    "f",
    "g"
  ],
  "linear_extensions": 30,
  "pair": [
    "c",
    "e"
  ],
  "trace": {
    "available": [
      {
        "choose": "a",
        "first_before_second": 11,
        "pair_state_after_choice": "unseen",
        "remaining_after_choice": [
          "b",
          "c",
          "d",
          "e",
          "f",
          "g"
        ],
        "second_before_first": 8,
        "subtrace": {
          "available": [
            {
              "choose": "b",
              "first_before_second": 7,
              "pair_state_after_choice": "unseen",
              "remaining_after_choice": [
                "c",
                "d",
                "e",
                "f",
                "g"
              ],
              "second_before_first": 4,
              "subtrace": {
                "available": [
                  {
                    "choose": "c",
                    "first_before_second": 3,
                    "pair_state_after_choice": "first_before_second",
                    "remaining_after_choice": [
                      "d",
                      "e",
                      "f",
                      "g"
                    ],
                    "second_before_first": 0
                  },
                  {
                    "choose": "d",
                    "first_before_second": 4,
                    "pair_state_after_choice": "unseen",
                    "remaining_after_choice": [
                      "c",
                      "e",
                      "f",
                      "g"
                    ],
                    "second_before_first": 4
                  }
                ],
                "first_before_second": 7,
                "pair_state": "unseen",
                "placed": [
                  "a",
                  "b"
                ],
                "second_before_first": 4
              }
            },
            {
              "choose": "d",
              "first_before_second": 4,
              "pair_state_after_choice": "unseen",
              "remaining_after_choice": [
                "b",
                "c",
                "e",
                "f",
                "g"
              ],
              "second_before_first": 4,
              "subtrace": {
                "available": [
                  {
                    "choose": "b",
                    "first_before_second": 4,
                    "pair_state_after_choice": "unseen",
                    "remaining_after_choice": [
                      "c",
                      "e",
                      "f",
                      "g"
                    ],
                    "second_before_first": 4
                  }
                ],
                "first_before_second": 4,
                "pair_state": "unseen",
                "placed": [
                  "a",
                  "d"
                ],
                "second_before_first": 4
              }
            }
          ],
          "first_before_second": 11,
          "pair_state": "unseen",
          "placed": [
            "a"
          ],
          "second_before_first": 8
        }
      },
      {
        "choose": "b",
        "first_before_second": 7,
        "pair_state_after_choice": "unseen",
        "remaining_after_choice": [
          "a",
          "c",
          "d",
          "e",
          "f",
          "g"
        ],
        "second_before_first": 4,
        "subtrace": {
          "available": [
            {
              "choose": "a",
              "first_before_second": 7,
              "pair_state_after_choice": "unseen",
              "remaining_after_choice": [
                "c",
                "d",
                "e",
                "f",
                "g"
              ],
              "second_before_first": 4,
              "subtrace": {
                "available": [
                  {
                    "choose": "c",
                    "first_before_second": 3,
                    "pair_state_after_choice": "first_before_second",
                    "remaining_after_choice": [
                      "d",
                      "e",
                      "f",
                      "g"
                    ],
                    "second_before_first": 0
                  },
                  {
                    "choose": "d",
                    "first_before_second": 4,
                    "pair_state_after_choice": "unseen",
                    "remaining_after_choice": [
                      "c",
                      "e",
                      "f",
                      "g"
                    ],
                    "second_before_first": 4
                  }
                ],
                "first_before_second": 7,
                "pair_state": "unseen",
                "placed": [
                  "a",
                  "b"
                ],
                "second_before_first": 4
              }
            }
          ],
          "first_before_second": 7,
          "pair_state": "unseen",
          "placed": [
            "b"
          ],
          "second_before_first": 4
        }
      }
    ],
    "first_before_second": 18,
    "pair_state": "unseen",
    "placed": [],
    "second_before_first": 12
  }
}
